{
"type": "FeatureCollection",
"name": "sampel_bus_station",
"crs": { "type": "name", "properties": { "name": "urn:ogc:def:crs:OGC:1.3:CRS84" } },
"features": [
{"type":"Feature","properties":{"id":"node/9843418012","amenity":"bus_station","bus":"yes","name":"Halte BRT Tentrem Mall","longitude":110.42242,"latitude":-6.98681},"geometry":{"type":"Point","coordinates":[110.4224187,-6.9868057]}},
{"type":"Feature","properties":{"id":"node/12736375403","amenity":"bus_station","bus":null,"name":"Cititrans Shuttle","longitude":110.41952,"latitude":-6.98973},"geometry":{"type":"Point","coordinates":[110.4195212,-6.9897297]}}
]
}
